lwlr/LLR.py
lwlr/__init__.py
lwlr/lwlr.py
lwlr-1.0.1.dist-info/LICENSE
lwlr-1.0.1.dist-info/METADATA
lwlr-1.0.1.dist-info/WHEEL
lwlr-1.0.1.dist-info/top_level.txt
lwlr-1.0.1.dist-info/RECORD
